zcrmsdk/__init__.py
zcrmsdk/src/__init__.py
zcrmsdk/src/json_details.json
zcrmsdk/src/com/__init__.py
zcrmsdk/src/com/zoho/__init__.py
zcrmsdk/src/com/zoho/api/__init__.py
zcrmsdk/src/com/zoho/api/authenticator/__init__.py
zcrmsdk/src/com/zoho/api/authenticator/oauth_token.py
zcrmsdk/src/com/zoho/api/authenticator/token.py
zcrmsdk/src/com/zoho/api/authenticator/store/__init__.py
zcrmsdk/src/com/zoho/api/authenticator/store/db_store.py
zcrmsdk/src/com/zoho/api/authenticator/store/file_store.py
zcrmsdk/src/com/zoho/api/authenticator/store/token_store.py
zcrmsdk/src/com/zoho/api/logger/__init__.py
zcrmsdk/src/com/zoho/api/logger/logger.py
zcrmsdk/src/com/zoho/crm/__init__.py
zcrmsdk/src/com/zoho/crm/api/__init__.py
zcrmsdk/src/com/zoho/crm/api/header.py
zcrmsdk/src/com/zoho/crm/api/header_map.py
zcrmsdk/src/com/zoho/crm/api/initializer.py
zcrmsdk/src/com/zoho/crm/api/param.py
zcrmsdk/src/com/zoho/crm/api/parameter_map.py
zcrmsdk/src/com/zoho/crm/api/request_proxy.py
zcrmsdk/src/com/zoho/crm/api/sdk_config.py
zcrmsdk/src/com/zoho/crm/api/user_signature.py
zcrmsdk/src/com/zoho/crm/api/assignment_rules/__init__.py
zcrmsdk/src/com/zoho/crm/api/assignment_rules/api_exception.py
zcrmsdk/src/com/zoho/crm/api/assignment_rules/assignment_rule.py
zcrmsdk/src/com/zoho/crm/api/assignment_rules/assignment_rules_operations.py
zcrmsdk/src/com/zoho/crm/api/assignment_rules/default_user.py
zcrmsdk/src/com/zoho/crm/api/assignment_rules/response_handler.py
zcrmsdk/src/com/zoho/crm/api/assignment_rules/response_wrapper.py
zcrmsdk/src/com/zoho/crm/api/attachments/__init__.py
zcrmsdk/src/com/zoho/crm/api/attachments/action_handler.py
zcrmsdk/src/com/zoho/crm/api/attachments/action_response.py
zcrmsdk/src/com/zoho/crm/api/attachments/action_wrapper.py
zcrmsdk/src/com/zoho/crm/api/attachments/api_exception.py
zcrmsdk/src/com/zoho/crm/api/attachments/attachment.py
zcrmsdk/src/com/zoho/crm/api/attachments/attachments_operations.py
zcrmsdk/src/com/zoho/crm/api/attachments/file_body_wrapper.py
zohocrmsdk2_1-3.0.0.dist-info/LICENSE
zohocrmsdk2_1-3.0.0.dist-info/METADATA
zohocrmsdk2_1-3.0.0.dist-info/WHEEL
zohocrmsdk2_1-3.0.0.dist-info/top_level.txt
zohocrmsdk2_1-3.0.0.dist-info/RECORD
